ldscripts/__init__.py
ldscripts-1.6.dist-info/METADATA
ldscripts-1.6.dist-info/WHEEL
ldscripts-1.6.dist-info/top_level.txt
ldscripts-1.6.dist-info/RECORD
