Metadata-Version: 2.1
Name: ldscripts
Version: 1.6
Summary: Scripts
Home-page: UNKNOWN
Author: Jack Vallis
Author-email: jack@lachlandickson.com
License: UNKNOWN
Platform: UNKNOWN
